MANIFEST.in
README.rst
setup.py
docs/HISTORY.txt
src/zope_lrr_analyzer.py
src/zope_lrr_analyzer.egg-info/PKG-INFO
src/zope_lrr_analyzer.egg-info/SOURCES.txt
src/zope_lrr_analyzer.egg-info/dependency_links.txt
src/zope_lrr_analyzer.egg-info/entry_points.txt
src/zope_lrr_analyzer.egg-info/not-zip-safe
src/zope_lrr_analyzer.egg-info/requires.txt
src/zope_lrr_analyzer.egg-info/top_level.txt