Metadata-Version: 1.0
Name: zope-lrr-analyzer
Version: 0.1
Summary: Analyze Zope instance log with haufe.requestmonitoring entries
Home-page: https://github.com/RedTurtle/zope_lrr_analyzer
Author: RedTurtle Technology
Author-email: sviluppoplone@redturtle.it
License: GPL
Keywords: file log process-time analyser access lrr zope
Platform: UNKNOWN
Classifier: Development Status :: 4 - Beta
Classifier: Intended Audience :: System Administrators
Classifier: License :: OSI Approved :: GNU General Public License (GPL)
Classifier: Operating System :: OS Independent
Classifier: Programming Language :: Python
Classifier: Programming Language :: Python :: 2.6
Classifier: Programming Language :: Python :: 2.7
Classifier: Framework :: Zope2
Classifier: Topic :: Utilities
Classifier: Topic :: Internet :: Log Analysis
